.gitignore
CHANGELOG.rst
LICENSE.txt
README.rst
nbval_sanitize.cfg
pytest.ini
ruff.toml
setup.py
test_requirements.txt
.github/workflows/test.yml
docs/.nojekyll
docs/Makefile
docs/README.rst
docs/acknowledgments.rst
docs/conf.py
docs/curvefits_example.nblink
docs/doc_requirements.txt
docs/hillcurve_example.nblink
docs/index.rst
docs/installation.rst
docs/package_index.rst
docs/_static/BloomLogo.jpg
neutcurve/__init__.py
neutcurve/colorschemes.py
neutcurve/curvefits.py
neutcurve/hillcurve.py
neutcurve/marimo_utils.py
neutcurve.egg-info/PKG-INFO
neutcurve.egg-info/SOURCES.txt
neutcurve.egg-info/dependency_links.txt
neutcurve.egg-info/requires.txt
neutcurve.egg-info/top_level.txt
notebooks/Doud_et_al_2018-neutdata.csv
notebooks/README.md
notebooks/curvefits_example.ipynb
notebooks/hillcurve_example.ipynb