Metadata-Version: 2.4
Name: neutcurve
Version: 2.3.0
Summary: Plot and fit neutralization curves.
Home-page: https://github.com/jbloomlab/neutcurve
Download-URL: https://github.com/jbloomlab/neutcurve/tarball/2.3.0
Author: Jesse Bloom
Author-email: jbloom@fredhutch.org
License: GPLv3
Platform: Linux and Mac OS X.
License-File: LICENSE.txt
Requires-Dist: dmslogo>=0.2.1
Requires-Dist: matplotlib>=3.0.0
Requires-Dist: openpyxl>=3.0
Requires-Dist: pandas>=1.0.1
Requires-Dist: pyyaml>=3.13
Requires-Dist: scipy>=1.1.0
Requires-Dist: xlrd>=1.2
Dynamic: author
Dynamic: author-email
Dynamic: description
Dynamic: download-url
Dynamic: home-page
Dynamic: license
Dynamic: license-file
Dynamic: platform
Dynamic: requires-dist
Dynamic: summary
